inputtino_web_client/__init__.py
inputtino_web_client/base_client.py
inputtino_web_client/cli.py
inputtino_web_client/keyboard.py
inputtino_web_client/models.py
inputtino_web_client/mouse.py
inputtino_web_client/py.typed
inputtino_web_client-0.1.0.dist-info/METADATA
inputtino_web_client-0.1.0.dist-info/WHEEL
inputtino_web_client-0.1.0.dist-info/entry_points.txt
inputtino_web_client-0.1.0.dist-info/RECORD
