Metadata-Version: 2.4
Name: inputtino-web-client
Version: 0.1.0
Summary: A Python library for controlling mouse and keyboard input through the Inputtino HTTP API.
Project-URL: Repository, https://github.com/Geson-anko/inputtino-web-client
Project-URL: Issues, https://github.com/Geson-anko/inputtino-web-client/issues
Author-email: GesonAnko <59220704+Geson-anko@users.noreply.github.com>
Keywords: automation,control,gui,keyboard,mouse
Classifier: Development Status :: 3 - Alpha
Classifier: Environment :: X11 Applications
Classifier: Intended Audience :: Developers
Classifier: License :: OSI Approved :: MIT License
Classifier: Natural Language :: English
Classifier: Natural Language :: Japanese
Classifier: Programming Language :: Python
Classifier: Programming Language :: Python :: 3
Classifier: Programming Language :: Python :: 3.12
Classifier: Programming Language :: Python :: 3.13
Requires-Python: >=3.12
Requires-Dist: httpx>=0.28.1
Requires-Dist: pydantic>=2.10.6
Provides-Extra: cli
Requires-Dist: cmd2>=2.5.11; extra == 'cli'
Requires-Dist: tyro>=0.9.13; extra == 'cli'
